feagi_connector_mujoco/__init__.py
feagi_connector_mujoco/__main__.py
feagi_connector_mujoco/capabilities.json
feagi_connector_mujoco/controller.py
feagi_connector_mujoco/humanoid.xml
feagi_connector_mujoco/mujoco_config_template.json
feagi_connector_mujoco/mujoco_helper.py
feagi_connector_mujoco/networking.json
feagi_connector_mujoco/requirements.txt
feagi_connector_mujoco/parser/__init__.py
feagi_connector_mujoco/parser/config_parser.py
feagi_connector_mujoco/parser/feagi_config_template.json
feagi_connector_mujoco/parser/mujoco_config_template.json
feagi_connector_mujoco-0.0.5.dist-info/LICENSE
feagi_connector_mujoco-0.0.5.dist-info/METADATA
feagi_connector_mujoco-0.0.5.dist-info/WHEEL
feagi_connector_mujoco-0.0.5.dist-info/top_level.txt
feagi_connector_mujoco-0.0.5.dist-info/RECORD
