Metadata-Version: 2.2
Name: feagi_connector_mujoco
Version: 0.0.5
Summary: Allow FEAGI controls mujoco
Home-page: https://github.com/feagi/feagi
Author: Neuraville Inc.
Author-email: feagi@neuraville.com
Project-URL: Bug Tracker, https://github.com/feagi/feagi/issues
Classifier: Programming Language :: Python :: 3 :: Only
Classifier: License :: OSI Approved :: Apache Software License
Classifier: Operating System :: OS Independent
Requires-Python: >=3.9
License-File: LICENSE
Requires-Dist: feagi-connector>=0.0.33
Requires-Dist: mujoco==3.2.3
